sensord/__init__.py
sensord/cli/__init__.py
sensord/cli/__main__.py
sensord/cli/client.py
sensord/cli/sen0311.py
sensord/cli/sen0395.py
sensord/common/__init__.py
sensord/common/paths.py
sensord/common/sen0311.py
sensord/common/sen0395.py
sensord/common/socket.py
sensord/service/__init__.py
sensord/service/__main__.py
sensord/service/api.py
sensord/service/cfg.py
sensord/service/err.py
sensord/service/log.py
sensord/service/mqtt.py
sensord/service/sen0311.py
sensord/service/sen0395.py
sensord/service/ws.py
sensord-0.4.0.dist-info/entry_points.txt
sensord-0.4.0.dist-info/licenses/LICENSE
sensord-0.4.0.dist-info/WHEEL
sensord-0.4.0.dist-info/METADATA
sensord-0.4.0.dist-info/RECORD
